simple_progress/__init__.py
simple_progress/exceptions.py
simple_progress/models.py
smooth_progress/__init__.py
smooth_progress/exceptions.py
smooth_progress/models.py
smooth_progress-0.2.0.dist-info/LICENSE
smooth_progress-0.2.0.dist-info/METADATA
smooth_progress-0.2.0.dist-info/WHEEL
smooth_progress-0.2.0.dist-info/top_level.txt
smooth_progress-0.2.0.dist-info/RECORD
