Metadata-Version: 2.1
Name: smooth-progress
Version: 0.2.0
Summary: A simple progress bar made primarily for my own personal use. Made from a combination of necessity and so much sloth that it overflowed into productivity.
Home-page: https://codeberg.org/MurdoMaclachlan/smooth_progress
Author: Murdo Maclachlan
Author-email: murdomaclachlan@duck.com
License: AGPLv3+
Classifier: Programming Language :: Python :: 3
Classifier: License :: OSI Approved :: GNU Affero General Public License v3 or later (AGPLv3+)
Classifier: Operating System :: OS Independent
License-File: LICENSE
